<?xml version="1.0" encoding="UTF-8"?>
<entity-engine-xml>
    <DataCategory dataCategoryId="BUSINESS" parentCategoryId="ROOT" categoryName="Business" lastUpdatedStamp="2019-01-10 00:54:22.0" lastUpdatedTxStamp="2019-01-10 00:54:22.0" createdStamp="2019-01-10 00:54:22.0" createdTxStamp="2019-01-10 00:54:22.0"/>
    <DataCategory dataCategoryId="BUS_MANU" parentCategoryId="BUSINESS" categoryName="Manufacturing" lastUpdatedStamp="2019-01-10 00:54:22.0" lastUpdatedTxStamp="2019-01-10 00:54:22.0" createdStamp="2019-01-10 00:54:22.0" createdTxStamp="2019-01-10 00:54:22.0"/>
    <DataCategory dataCategoryId="BUS_RETAIL" parentCategoryId="BUSINESS" categoryName="Retail" lastUpdatedStamp="2019-01-10 00:54:22.0" lastUpdatedTxStamp="2019-01-10 00:54:22.0" createdStamp="2019-01-10 00:54:22.0" createdTxStamp="2019-01-10 00:54:22.0"/>
    <DataCategory dataCategoryId="BUS_SERVICE" parentCategoryId="BUSINESS" categoryName="Service" lastUpdatedStamp="2019-01-10 00:54:22.0" lastUpdatedTxStamp="2019-01-10 00:54:22.0" createdStamp="2019-01-10 00:54:22.0" createdTxStamp="2019-01-10 00:54:22.0"/>
    <DataCategory dataCategoryId="FINANCIAL" parentCategoryId="ROOT" categoryName="Financial" lastUpdatedStamp="2019-01-10 00:54:22.0" lastUpdatedTxStamp="2019-01-10 00:54:22.0" createdStamp="2019-01-10 00:54:22.0" createdTxStamp="2019-01-10 00:54:22.0"/>
    <DataCategory dataCategoryId="LEGAL" parentCategoryId="ROOT" categoryName="Legal" lastUpdatedStamp="2019-01-10 00:54:22.0" lastUpdatedTxStamp="2019-01-10 00:54:22.0" createdStamp="2019-01-10 00:54:22.0" createdTxStamp="2019-01-10 00:54:22.0"/>
    <DataCategory dataCategoryId="PERSONAL" parentCategoryId="ROOT" categoryName="Personal" lastUpdatedStamp="2019-01-10 00:54:22.0" lastUpdatedTxStamp="2019-01-10 00:54:22.0" createdStamp="2019-01-10 00:54:22.0" createdTxStamp="2019-01-10 00:54:22.0"/>
    <DataCategory dataCategoryId="POLITICAL" parentCategoryId="ROOT" categoryName="Political" lastUpdatedStamp="2019-01-10 00:54:22.0" lastUpdatedTxStamp="2019-01-10 00:54:22.0" createdStamp="2019-01-10 00:54:22.0" createdTxStamp="2019-01-10 00:54:22.0"/>
    <DataCategory dataCategoryId="ROOT" lastUpdatedStamp="2019-01-10 00:54:22.0" lastUpdatedTxStamp="2019-01-10 00:54:22.0" createdStamp="2019-01-10 00:54:22.0" createdTxStamp="2019-01-10 00:54:22.0"/>
    <DataCategory dataCategoryId="TECHNOLOGY" parentCategoryId="ROOT" categoryName="Technology" lastUpdatedStamp="2019-01-10 00:54:22.0" lastUpdatedTxStamp="2019-01-10 00:54:22.0" createdStamp="2019-01-10 00:54:22.0" createdTxStamp="2019-01-10 00:54:22.0"/>
    <DataCategory dataCategoryId="TECH_HARD" parentCategoryId="TECHNOLOGY" categoryName="Hardware" lastUpdatedStamp="2019-01-10 00:54:22.0" lastUpdatedTxStamp="2019-01-10 00:54:22.0" createdStamp="2019-01-10 00:54:22.0" createdTxStamp="2019-01-10 00:54:22.0"/>
    <DataCategory dataCategoryId="TECH_SERV" parentCategoryId="TECHNOLOGY" categoryName="Service" lastUpdatedStamp="2019-01-10 00:54:22.0" lastUpdatedTxStamp="2019-01-10 00:54:22.0" createdStamp="2019-01-10 00:54:22.0" createdTxStamp="2019-01-10 00:54:22.0"/>
    <DataCategory dataCategoryId="TECH_SOFT" parentCategoryId="TECHNOLOGY" categoryName="Software" lastUpdatedStamp="2019-01-10 00:54:22.0" lastUpdatedTxStamp="2019-01-10 00:54:22.0" createdStamp="2019-01-10 00:54:22.0" createdTxStamp="2019-01-10 00:54:22.0"/>
    <DataCategory dataCategoryId="TECH_SOFT_JAVA" parentCategoryId="TECH_SOFT" categoryName="Java" lastUpdatedStamp="2019-01-10 00:54:22.0" lastUpdatedTxStamp="2019-01-10 00:54:22.0" createdStamp="2019-01-10 00:54:22.0" createdTxStamp="2019-01-10 00:54:22.0"/>
    <DataCategory dataCategoryId="TECH_SOFT_LINUX" parentCategoryId="TECH_SOFT" categoryName="Linux" lastUpdatedStamp="2019-01-10 00:54:22.0" lastUpdatedTxStamp="2019-01-10 00:54:22.0" createdStamp="2019-01-10 00:54:22.0" createdTxStamp="2019-01-10 00:54:22.0"/>
    <DataCategory dataCategoryId="TECH_SOFT_OFBIZ" parentCategoryId="TECH_SOFT" categoryName="Apache OFBiz" lastUpdatedStamp="2019-01-10 00:54:22.0" lastUpdatedTxStamp="2019-01-10 00:54:22.0" createdStamp="2019-01-10 00:54:22.0" createdTxStamp="2019-01-10 00:54:22.0"/>
    <DataCategory dataCategoryId="TEMPLATE" parentCategoryId="ROOT" categoryName="Template" lastUpdatedStamp="2019-01-10 00:54:22.0" lastUpdatedTxStamp="2019-01-10 00:54:22.0" createdStamp="2019-01-10 00:54:22.0" createdTxStamp="2019-01-10 00:54:22.0"/>
</entity-engine-xml>
