<?xml version="1.0" encoding="UTF-8"?>
<entity-engine-xml>
    <ProductStoreEmailSetting productStoreId="9000" emailType="CONT_EMAIL_TEMPLATE" bodyScreenLocation="component://ecommerce/widget/EmailContactListScreens.xml#ContactListEmailTemplate" lastUpdatedStamp="2019-01-10 01:11:30.0" lastUpdatedTxStamp="2019-01-10 01:11:30.0" createdStamp="2019-01-10 01:11:30.0" createdTxStamp="2019-01-10 01:11:30.0"/>
    <ProductStoreEmailSetting productStoreId="9000" emailType="CONT_NOTI_EMAIL" bodyScreenLocation="component://ecommerce/widget/EmailContactListScreens.xml#ContactUsEmailNotification" fromAddress="ofbiztest@example.com" subject="Contact-us Information Notification" lastUpdatedStamp="2019-01-10 01:11:30.0" lastUpdatedTxStamp="2019-01-10 01:11:30.0" createdStamp="2019-01-10 01:11:30.0" createdTxStamp="2019-01-10 01:11:30.0"/>
    <ProductStoreEmailSetting productStoreId="9000" emailType="PARTY_REGIS_CONFIRM" bodyScreenLocation="component://party/widget/partymgr/EmailPartyScreens.xml#CreatePartyNotification" fromAddress="ofbiztest@example.com" bccAddress="ofbiztest@example.com" subject="New Account Created" lastUpdatedStamp="2019-01-10 01:11:30.0" lastUpdatedTxStamp="2019-01-10 01:11:30.0" createdStamp="2019-01-10 01:11:30.0" createdTxStamp="2019-01-10 01:11:30.0"/>
    <ProductStoreEmailSetting productStoreId="9000" emailType="PRDS_CUST_ACTIVATED" bodyScreenLocation="component://party/widget/partymgr/EmailPartyScreens.xml#AccountActivatedNotification" fromAddress="ofbiztest@example.com" bccAddress="ofbiztest@example.com" subject="Account Activated" lastUpdatedStamp="2019-01-10 01:11:30.0" lastUpdatedTxStamp="2019-01-10 01:11:30.0" createdStamp="2019-01-10 01:11:30.0" createdTxStamp="2019-01-10 01:11:30.0"/>
    <ProductStoreEmailSetting productStoreId="9000" emailType="PRDS_CUST_REGISTER" bodyScreenLocation="component://party/widget/partymgr/EmailPartyScreens.xml#CreatePartyNotification" fromAddress="ofbiztest@example.com" bccAddress="ofbiztest@example.com" subject="New Account Created" lastUpdatedStamp="2019-01-10 01:11:30.0" lastUpdatedTxStamp="2019-01-10 01:11:30.0" createdStamp="2019-01-10 01:11:30.0" createdTxStamp="2019-01-10 01:11:30.0"/>
    <ProductStoreEmailSetting productStoreId="9000" emailType="PRDS_EMAIL_VERIFY" bodyScreenLocation="component://party/widget/partymgr/EmailPartyScreens.xml#VerifyEmailAddressNotification" fromAddress="ofbiztest@example.com" bccAddress="ofbiztest@example.com" subject="Email Address Verification" lastUpdatedStamp="2019-01-10 01:11:30.0" lastUpdatedTxStamp="2019-01-10 01:11:30.0" createdStamp="2019-01-10 01:11:30.0" createdTxStamp="2019-01-10 01:11:30.0"/>
    <ProductStoreEmailSetting productStoreId="9000" emailType="PRDS_GC_PURCHASE" bodyScreenLocation="component://ecommerce/widget/EmailGiftCardScreens.xml#GiftCardPurchase" fromAddress="ofbiztest@example.com" subject="A Gift From ${senderName}!" lastUpdatedStamp="2019-01-10 01:11:30.0" lastUpdatedTxStamp="2019-01-10 01:11:30.0" createdStamp="2019-01-10 01:11:30.0" createdTxStamp="2019-01-10 01:11:30.0"/>
    <ProductStoreEmailSetting productStoreId="9000" emailType="PRDS_GC_RELOAD" bodyScreenLocation="component://ecommerce/widget/EmailGiftCardScreens.xml#GiftCardReload" fromAddress="ofbiztest@example.com" subject="Gift Card Reload Results" lastUpdatedStamp="2019-01-10 01:11:30.0" lastUpdatedTxStamp="2019-01-10 01:11:30.0" createdStamp="2019-01-10 01:11:30.0" createdTxStamp="2019-01-10 01:11:30.0"/>
    <ProductStoreEmailSetting productStoreId="9000" emailType="PRDS_ODR_BACKORDER" bodyScreenLocation="component://ecommerce/widget/EmailOrderScreens.xml#BackorderNotice" fromAddress="ofbiztest@example.com" subject="OFBiz Demo - Backorder Notification #${orderId}" lastUpdatedStamp="2019-01-10 01:11:30.0" lastUpdatedTxStamp="2019-01-10 01:11:30.0" createdStamp="2019-01-10 01:11:30.0" createdTxStamp="2019-01-10 01:11:30.0"/>
    <ProductStoreEmailSetting productStoreId="9000" emailType="PRDS_ODR_CHANGE" bodyScreenLocation="component://ecommerce/widget/EmailOrderScreens.xml#OrderChangeNotice" fromAddress="ofbiztest@example.com" subject="OFBiz Demo - Order Change Notification #${orderId}" lastUpdatedStamp="2019-01-10 01:11:30.0" lastUpdatedTxStamp="2019-01-10 01:11:30.0" createdStamp="2019-01-10 01:11:30.0" createdTxStamp="2019-01-10 01:11:30.0"/>
    <ProductStoreEmailSetting productStoreId="9000" emailType="PRDS_ODR_COMPLETE" bodyScreenLocation="component://ecommerce/widget/EmailOrderScreens.xml#OrderCompleteNotice" fromAddress="ofbiztest@example.com" subject="OFBiz Demo - Your Order Is Complete #${orderId}" lastUpdatedStamp="2019-01-10 01:11:30.0" lastUpdatedTxStamp="2019-01-10 01:11:30.0" createdStamp="2019-01-10 01:11:30.0" createdTxStamp="2019-01-10 01:11:30.0"/>
    <ProductStoreEmailSetting productStoreId="9000" emailType="PRDS_ODR_CONFIRM" bodyScreenLocation="component://ecommerce/widget/EmailOrderScreens.xml#OrderConfirmNotice" xslfoAttachScreenLocation="component://ecommerce/widget/EmailOrderScreens.xml#OrderConfirmNoticePdf" fromAddress="ofbiztest@example.com" bccAddress="ofbiztest@example.com" subject="OFBiz Demo - Order Confirmation #${orderId}" lastUpdatedStamp="2019-01-10 01:11:30.0" lastUpdatedTxStamp="2019-01-10 01:11:30.0" createdStamp="2019-01-10 01:11:30.0" createdTxStamp="2019-01-10 01:11:30.0"/>
    <ProductStoreEmailSetting productStoreId="9000" emailType="PRDS_ODR_PAYRETRY" bodyScreenLocation="component://ecommerce/widget/EmailOrderScreens.xml#PaymentRetryNotice" fromAddress="ofbiztest@example.com" subject="OFBiz Demo - Order Payment Notification #${orderId}" lastUpdatedStamp="2019-01-10 01:11:30.0" lastUpdatedTxStamp="2019-01-10 01:11:30.0" createdStamp="2019-01-10 01:11:30.0" createdTxStamp="2019-01-10 01:11:30.0"/>
    <ProductStoreEmailSetting productStoreId="9000" emailType="PRDS_ODR_SHIP_COMPLT" bodyScreenLocation="component://ecommerce/widget/EmailOrderScreens.xml#ShipmentCompleteNotice" fromAddress="ofbiztest@example.com" subject="OFBiz Demo - Shipment Complete Notification #${orderId}" lastUpdatedStamp="2019-01-10 01:11:30.0" lastUpdatedTxStamp="2019-01-10 01:11:30.0" createdStamp="2019-01-10 01:11:30.0" createdTxStamp="2019-01-10 01:11:30.0"/>
    <ProductStoreEmailSetting productStoreId="9000" emailType="PRDS_PWD_RETRIEVE" bodyScreenLocation="component://securityext/widget/EmailSecurityScreens.xml#PasswordEmail" fromAddress="ofbiztest@example.com" subject="OFBiz Demo - Password Reminder (${userLogin.userLoginId})" lastUpdatedStamp="2019-01-10 01:11:30.0" lastUpdatedTxStamp="2019-01-10 01:11:30.0" createdStamp="2019-01-10 01:11:30.0" createdTxStamp="2019-01-10 01:11:30.0"/>
    <ProductStoreEmailSetting productStoreId="9000" emailType="PRDS_QUO_CONFIRM" bodyScreenLocation="component://order/widget/ordermgr/QuoteScreens.xml#ViewQuoteSimple" xslfoAttachScreenLocation="component://order/widget/ordermgr/QuoteScreens.xml#QuoteReport" fromAddress="ofbiztest@example.com" bccAddress="ofbiztest@example.com" subject="OFBiz Demo - Quote Confirmation #${quoteId}" lastUpdatedStamp="2019-01-10 01:11:30.0" lastUpdatedTxStamp="2019-01-10 01:11:30.0" createdStamp="2019-01-10 01:11:30.0" createdTxStamp="2019-01-10 01:11:30.0"/>
    <ProductStoreEmailSetting productStoreId="9000" emailType="PRDS_RTN_ACCEPT" bodyScreenLocation="component://ecommerce/widget/EmailReturnScreens.xml#ReturnAccept" xslfoAttachScreenLocation="component://order/widget/ordermgr/OrderPrintScreens.xml#ReturnPDF" fromAddress="ofbiztest@example.com" subject="OFBiz Demo - Return Accepted #${returnHeader.returnId}" lastUpdatedStamp="2019-01-10 01:11:30.0" lastUpdatedTxStamp="2019-01-10 01:11:30.0" createdStamp="2019-01-10 01:11:30.0" createdTxStamp="2019-01-10 01:11:30.0"/>
    <ProductStoreEmailSetting productStoreId="9000" emailType="PRDS_RTN_CANCEL" bodyScreenLocation="component://ecommerce/widget/EmailReturnScreens.xml#ReturnCancel" xslfoAttachScreenLocation="component://order/widget/ordermgr/OrderPrintScreens.xml#ReturnPDF" fromAddress="ofbiztest@example.com" subject="OFBiz Demo - Return Cancelled #${returnHeader.returnId}" lastUpdatedStamp="2019-01-10 01:11:30.0" lastUpdatedTxStamp="2019-01-10 01:11:30.0" createdStamp="2019-01-10 01:11:30.0" createdTxStamp="2019-01-10 01:11:30.0"/>
    <ProductStoreEmailSetting productStoreId="9000" emailType="PRDS_RTN_COMPLETE" bodyScreenLocation="component://ecommerce/widget/EmailReturnScreens.xml#ReturnComplete" xslfoAttachScreenLocation="component://order/widget/ordermgr/OrderPrintScreens.xml#ReturnPDF" fromAddress="ofbiztest@example.com" subject="OFBiz Demo - Return Completed #${returnHeader.returnId}" lastUpdatedStamp="2019-01-10 01:11:30.0" lastUpdatedTxStamp="2019-01-10 01:11:30.0" createdStamp="2019-01-10 01:11:30.0" createdTxStamp="2019-01-10 01:11:30.0"/>
    <ProductStoreEmailSetting productStoreId="9000" emailType="PRDS_TELL_FRIEND" bodyScreenLocation="component://ecommerce/widget/EmailProductScreens.xml#TellFriend" fromAddress="ofbiztest@example.com" subject="${sendFrom} has sent you a link!" lastUpdatedStamp="2019-01-10 01:11:30.0" lastUpdatedTxStamp="2019-01-10 01:11:30.0" createdStamp="2019-01-10 01:11:30.0" createdTxStamp="2019-01-10 01:11:30.0"/>
    <ProductStoreEmailSetting productStoreId="9000" emailType="SUB_CONT_LIST_NOTI" bodyScreenLocation="component://ecommerce/widget/EmailContactListScreens.xml#ContactListSubscribeEmail" fromAddress="ofbiztest@example.com" subject="Subscribe Contact List" lastUpdatedStamp="2019-01-10 01:11:30.0" lastUpdatedTxStamp="2019-01-10 01:11:30.0" createdStamp="2019-01-10 01:11:30.0" createdTxStamp="2019-01-10 01:11:30.0"/>
    <ProductStoreEmailSetting productStoreId="9000" emailType="UNSUB_CONT_LIST_NOTI" bodyScreenLocation="component://ecommerce/widget/EmailContactListScreens.xml#ContactListUnsubscribeEmail" fromAddress="ofbiztest@example.com" subject="Unsubscribe Contact List" lastUpdatedStamp="2019-01-10 01:11:30.0" lastUpdatedTxStamp="2019-01-10 01:11:30.0" createdStamp="2019-01-10 01:11:30.0" createdTxStamp="2019-01-10 01:11:30.0"/>
    <ProductStoreEmailSetting productStoreId="9000" emailType="UNSUB_CONT_LIST_VERI" bodyScreenLocation="component://ecommerce/widget/EmailContactListScreens.xml#ContactListUnsubscribeVerifyEmail" fromAddress="ofbiztest@example.com" subject="Verify Unsubscribe Contact List" lastUpdatedStamp="2019-01-10 01:11:30.0" lastUpdatedTxStamp="2019-01-10 01:11:30.0" createdStamp="2019-01-10 01:11:30.0" createdTxStamp="2019-01-10 01:11:30.0"/>
    <ProductStoreEmailSetting productStoreId="9000" emailType="UPD_PRSNL_INF_CNFRM" bodyScreenLocation="component://party/widget/partymgr/EmailPartyScreens.xml#ChangePersonalInfoNotification" fromAddress="ofbiztest@example.com" bccAddress="ofbiztest@example.com" subject="Personal Information Updated" lastUpdatedStamp="2019-01-10 01:11:30.0" lastUpdatedTxStamp="2019-01-10 01:11:30.0" createdStamp="2019-01-10 01:11:30.0" createdTxStamp="2019-01-10 01:11:30.0"/>
    <ProductStoreEmailSetting productStoreId="RentalStore" emailType="PRDS_GC_PURCHASE" bodyScreenLocation="component://ecommerce/widget/EmailGiftCardScreens.xml#GiftCardPurchase" fromAddress="ofbiztest@example.com" subject="A Gift From ${senderName}!" lastUpdatedStamp="2019-01-10 01:11:40.0" lastUpdatedTxStamp="2019-01-10 01:11:40.0" createdStamp="2019-01-10 01:11:40.0" createdTxStamp="2019-01-10 01:11:40.0"/>
    <ProductStoreEmailSetting productStoreId="RentalStore" emailType="PRDS_GC_RELOAD" bodyScreenLocation="component://ecommerce/widget/EmailGiftCardScreens.xml#GiftCardReload" fromAddress="ofbiztest@example.com" subject="Gift Card Reload Results" lastUpdatedStamp="2019-01-10 01:11:40.0" lastUpdatedTxStamp="2019-01-10 01:11:40.0" createdStamp="2019-01-10 01:11:40.0" createdTxStamp="2019-01-10 01:11:40.0"/>
    <ProductStoreEmailSetting productStoreId="RentalStore" emailType="PRDS_ODR_BACKORDER" bodyScreenLocation="component://ecommerce/widget/EmailOrderScreens.xml#BackorderNotice" fromAddress="ofbiztest@example.com" subject="OFBiz Demo - Backorder Notification #${orderId}" lastUpdatedStamp="2019-01-10 01:11:40.0" lastUpdatedTxStamp="2019-01-10 01:11:40.0" createdStamp="2019-01-10 01:11:40.0" createdTxStamp="2019-01-10 01:11:40.0"/>
    <ProductStoreEmailSetting productStoreId="RentalStore" emailType="PRDS_ODR_CHANGE" bodyScreenLocation="component://ecommerce/widget/EmailOrderScreens.xml#OrderChangeNotice" fromAddress="ofbiztest@example.com" subject="OFBiz Demo - Order Change Notification #${orderId}" lastUpdatedStamp="2019-01-10 01:11:40.0" lastUpdatedTxStamp="2019-01-10 01:11:40.0" createdStamp="2019-01-10 01:11:40.0" createdTxStamp="2019-01-10 01:11:40.0"/>
    <ProductStoreEmailSetting productStoreId="RentalStore" emailType="PRDS_ODR_COMPLETE" bodyScreenLocation="component://ecommerce/widget/EmailOrderScreens.xml#OrderCompleteNotice" fromAddress="ofbiztest@example.com" subject="OFBiz Demo - Your Order Is Complete #${orderId}" lastUpdatedStamp="2019-01-10 01:11:40.0" lastUpdatedTxStamp="2019-01-10 01:11:40.0" createdStamp="2019-01-10 01:11:40.0" createdTxStamp="2019-01-10 01:11:40.0"/>
    <ProductStoreEmailSetting productStoreId="RentalStore" emailType="PRDS_ODR_CONFIRM" bodyScreenLocation="component://ecommerce/widget/EmailOrderScreens.xml#OrderConfirmNotice" xslfoAttachScreenLocation="component://ecommerce/widget/EmailOrderScreens.xml#OrderConfirmNoticePdf" fromAddress="ofbiztest@example.com" bccAddress="ofbiztest@example.com" subject="OFBiz Demo - Order Confirmation #${orderId}" lastUpdatedStamp="2019-01-10 01:11:40.0" lastUpdatedTxStamp="2019-01-10 01:11:40.0" createdStamp="2019-01-10 01:11:40.0" createdTxStamp="2019-01-10 01:11:40.0"/>
    <ProductStoreEmailSetting productStoreId="RentalStore" emailType="PRDS_ODR_PAYRETRY" bodyScreenLocation="component://ecommerce/widget/EmailOrderScreens.xml#PaymentRetryNotice" fromAddress="ofbiztest@example.com" subject="OFBiz Demo - Order Payment Notification #${orderId}" lastUpdatedStamp="2019-01-10 01:11:40.0" lastUpdatedTxStamp="2019-01-10 01:11:40.0" createdStamp="2019-01-10 01:11:40.0" createdTxStamp="2019-01-10 01:11:40.0"/>
    <ProductStoreEmailSetting productStoreId="RentalStore" emailType="PRDS_PWD_RETRIEVE" bodyScreenLocation="component://securityext/widget/EmailSecurityScreens.xml#PasswordEmail" fromAddress="ofbiztest@example.com" subject="OFBiz Demo - Password Reminder (${userLoginId})" lastUpdatedStamp="2019-01-10 01:11:40.0" lastUpdatedTxStamp="2019-01-10 01:11:40.0" createdStamp="2019-01-10 01:11:40.0" createdTxStamp="2019-01-10 01:11:40.0"/>
    <ProductStoreEmailSetting productStoreId="RentalStore" emailType="PRDS_RTN_ACCEPT" bodyScreenLocation="component://ecommerce/widget/EmailReturnScreens.xml#ReturnAccept" fromAddress="ofbiztest@example.com" subject="OFBiz Demo - Return Accepted #${returnHeader.returnId}" lastUpdatedStamp="2019-01-10 01:11:40.0" lastUpdatedTxStamp="2019-01-10 01:11:40.0" createdStamp="2019-01-10 01:11:40.0" createdTxStamp="2019-01-10 01:11:40.0"/>
    <ProductStoreEmailSetting productStoreId="RentalStore" emailType="PRDS_RTN_CANCEL" bodyScreenLocation="component://ecommerce/widget/EmailReturnScreens.xml#ReturnCancel" fromAddress="ofbiztest@example.com" subject="OFBiz Demo - Return Cancelled #${returnHeader.returnId}" lastUpdatedStamp="2019-01-10 01:11:40.0" lastUpdatedTxStamp="2019-01-10 01:11:40.0" createdStamp="2019-01-10 01:11:40.0" createdTxStamp="2019-01-10 01:11:40.0"/>
    <ProductStoreEmailSetting productStoreId="RentalStore" emailType="PRDS_RTN_COMPLETE" bodyScreenLocation="component://ecommerce/widget/EmailReturnScreens.xml#ReturnComplete" fromAddress="ofbiztest@example.com" subject="OFBiz Demo - Return Completed #${returnHeader.returnId}" lastUpdatedStamp="2019-01-10 01:11:40.0" lastUpdatedTxStamp="2019-01-10 01:11:40.0" createdStamp="2019-01-10 01:11:40.0" createdTxStamp="2019-01-10 01:11:40.0"/>
    <ProductStoreEmailSetting productStoreId="RentalStore" emailType="PRDS_TELL_FRIEND" bodyScreenLocation="component://ecommerce/widget/EmailProductScreens.xml#TellFriend" fromAddress="ofbiztest@example.com" subject="${sendFrom} has sent you a link!" lastUpdatedStamp="2019-01-10 01:11:40.0" lastUpdatedTxStamp="2019-01-10 01:11:40.0" createdStamp="2019-01-10 01:11:40.0" createdTxStamp="2019-01-10 01:11:40.0"/>
</entity-engine-xml>
